zk/__init__.py
zk/core.py
zk_dist-0.3.0.dist-info/licenses/LICENSE
zk_dist-0.3.0.dist-info/METADATA
zk_dist-0.3.0.dist-info/WHEEL
zk_dist-0.3.0.dist-info/top_level.txt
zk_dist-0.3.0.dist-info/RECORD
