Metadata-Version: 2.4
Name: zk-dist
Version: 0.3.0
Summary: 一个示例 Python 包，提供简单功能。
Author-email: Karl_PyPI <author@example.com>
Maintainer-email: Karl_PyPI <maintainer@example.com>
License-Expression: MIT
Classifier: Programming Language :: Python :: 3
Classifier: Operating System :: OS Independent
Requires-Python: >=3.8
License-File: LICENSE
Requires-Dist: requests>=2.25.1
Requires-Dist: numpy>=1.21.0
Dynamic: license-file
